{"data_version":"0.1.0-dev","query":{"key":"ADA","in":"slp1","out":"iast","dicts":["mw","pwg","ap90"]},"results":[{"dict":"mw","L":"24098","sense_ids":["mw.24098.1@0.1.0-dev","mw.24098.2@0.1.0-dev","mw.24098.3@0.1.0-dev","mw.24098.4@0.1.0-dev","mw.24098.5@0.1.0-dev","mw.24098.6@0.1.0-dev","mw.24098.7@0.1.0-dev","mw.24098.8@0.1.0-dev","mw.24098.9@0.1.0-dev","mw.24098.10@0.1.0-dev","mw.24098.11@0.1.0-dev","mw.24098.12@0.1.0-dev","mw.24098.13@0.1.0-dev","mw.24098.14@0.1.0-dev","mw.24098.15@0.1.0-dev","mw.24098.16@0.1.0-dev","mw.24098.17@0.1.0-dev","mw.24098.18@0.1.0-dev","mw.24098.19@0.1.0-dev"],"scan_url":"https://sanskrit-lexicon.uni-koeln.de/scans/MWScan/2020/web/webtc/servepdf.php?page=138","headword":"ādhā","rendered_html":"<span class='sdata'>ā-√dhā</span> <span>P.</span> <span>Ā.</span> <span class='sdata'>-dadhāti</span>, <span class='sdata'>-dhatte</span> (in the later language usually <span>Ā.</span>), 1. <span>sg.</span> <span class='sdata'>ā-dadhāmi</span>, &nbsp;<span class='ls'>AV. ii, 10, 5</span>&nbsp;, &c.; <div style='margin-top:0.6em;'></div></div> <strong><span>Impv.</span></strong> 2. <span>sg.</span> <span class='sdata'>ā-dhehi</span>, &nbsp;<span class='ls'>AV. vi, 26, 1</span>&nbsp;, &c.; <div style='margin-top:0.6em;'></div></div> <strong><span>pf.</span></strong> 3. <span>pl.</span> <span class='sdata'>-dadhus</span>, &nbsp;<span class='ls'>RV. viii, 103, 1</span>&nbsp;, &c.; <div style='margin-top:0.6em;'></div></div> <strong><span>aor.</span></strong> 3. <span>pl.</span> <span class='sdata'>ā</span>-Dus, &nbsp;<span class='ls'>RV. iv, 6, 6</span>&nbsp;, &c.; <div style='margin-top:0.6em;'></div></div> <strong><span>p.</span></strong> <span class='sdata'>-dadhāna</span>, <span>p.</span> <span>Pass.</span> <span class='sdata'>-dhīyamāna</span> (in <span>comp.</span>, <span>e.g.</span> <span class='sdata'>ā-dhīyamāna-citta</span>, &nbsp;<span class='ls'>Rājat. v, 164</span>&nbsp;); <div style='margin-top:0.6em;'></div></div> <strong><span>perf.</span></strong> <span class='sdata'>-dadhau</span>, &c.; <div style='margin-top:0.6em;'></div></div> [see under √<span class='hom' title='Homonym'>1.</span> <span class='sdata'>dhā</span>], (<span>P.</span> and <span>Ā.</span>) to place on, put down, deposit, put; <div style='margin-top:0.6em;'></div></div>to impregnate, instil (<span>e.g.</span> good sentiments), impress, direct; <div style='margin-top:0.6em;'></div></div>to apply, appoint, &nbsp;<span class='ls'>RV.</span>&nbsp;; &nbsp;<span class='ls'>AV.</span>&nbsp;; &nbsp;<span class='ls'>ŚBr.</span>&nbsp;; &nbsp;<span class='ls'>MBh.</span>&nbsp; &c.; <div style='margin-top:0.6em;'></div></div>to add (fuel to fire), &nbsp;<span class='ls'>RV.</span>&nbsp;; &nbsp;<span class='ls'>ŚBr.</span>&nbsp;; &nbsp;<span class='ls'>ĀśvGṛ.</span>&nbsp;; &nbsp;<span class='ls'>PārGṛ.</span>&nbsp; &c.; <div style='margin-top:0.6em;'></div></div>to give or deposit in pledge, stake (money), &nbsp;<span class='ls'>RV.</span>&nbsp;; <div style='margin-top:0.6em;'></div></div>to give, supply, lend, deliver, &nbsp;<span class='ls'>RV.</span>&nbsp;; &nbsp;<span class='ls'>AV.</span>&nbsp;; &nbsp;<span class='ls'>PārGṛ.</span>&nbsp;; &nbsp;<span class='ls'>BhP.</span>&nbsp; &c.; <div style='margin-top:0.6em;'></div></div>to accept, receive, &nbsp;<span class='ls'>RV.</span>&nbsp;; &nbsp;<span class='ls'>AV.</span>&nbsp;; &nbsp;<span class='ls'>MBh.</span>&nbsp;; &nbsp;<span class='ls'>BhP.</span>&nbsp; &c.; <div style='margin-top:0.6em;'></div></div>to make, constitute, effect, &nbsp;<span class='ls'>Ragh.</span>&nbsp;; &nbsp;<span class='ls'>Mālav.</span>&nbsp;; &nbsp;<span class='ls'>Rājat.</span>&nbsp; &c.; <div style='margin-top:0.6em;'></div></div> (only <span>Ā.</span>) to keep, preserve, appropriate to one's self, hold, possess, take; <div style='margin-top:0.6em;'></div></div>to conceive (as a woman), get children, &nbsp;<span class='ls'>RV.</span>&nbsp; &c.: <div style='margin-top:0.6em;'></div></div><strong><span>Caus.</span></strong> <span class='sdata'>-dhāpayati</span>, to cause to put: <div style='margin-top:0.6em;'></div></div><strong><span>Desid.</span></strong> <span>Ā.</span> <span class='sdata'>-dhitsate</span>, to wish to kindle (a fire), &nbsp;<span class='ls'>TBr.</span>&nbsp; : <div style='margin-top:0.6em;'></div></div><span>P.</span> (<span>p.</span> <span class='sdata'>-dhitsat</span>) to be about to take up (a stick for punishing), &nbsp;<span class='ls'>MBh. xii, 3170.</span>&nbsp;","evidence":{"band":2,"band_label":"frequent -- learn early","rank_all":1010,"count_all":704,"first_era":"Vedic","genre":null,"example":{"sa":"ādadhe","ru":"вложила","work":"01_atharvaveda","passage":"28.3","kind":"translation","source":"corpus_lexicon.jsonl (pwg_ru Phase 4, SanskritLexicography/RussianTranslation)"},"badges":[{"field":"band","value":2,"label":"frequent -- learn early","source":"kosha frequency layer, rank_all (DCS archive.sqlite M9 via VisualDCS)"},{"field":"count_all","value":704,"label":"704 attestations in DCS","source":"DCS archive.sqlite M9 (VisualDCS)"},{"field":"first_era","value":"Vedic","label":"first attested: Vedic","source":"DCS archive.sqlite M9 (VisualDCS)"},{"field":"genre","value":null,"label":"genre sketch not derivable from current DCS extraction (only a chronological period vector is stored, no per-genre breakdown)","source":"n/a -- gap documented, not fabricated (see app/evidence.py)"}]}},{"dict":"ap90","L":"6203","sense_ids":["ap90.6203.1@0.1.0-dev","ap90.6203.2@0.1.0-dev","ap90.6203.3@0.1.0-dev","ap90.6203.4@0.1.0-dev","ap90.6203.5@0.1.0-dev","ap90.6203.6@0.1.0-dev","ap90.6203.7@0.1.0-dev","ap90.6203.8@0.1.0-dev","ap90.6203.9@0.1.0-dev","ap90.6203.10@0.1.0-dev"],"scan_url":"https://sanskrit-lexicon.uni-koeln.de/scans/AP90Scan/2020/web/webtc/servepdf.php?page=238","headword":"ādhā","rendered_html":"<span class='sdata'>ādhā</span> 3 <span>U.</span> <div style='margin-top:0.6em;'></div></div><strong>1</strong> To put, place, deposit, implant, lodge; <span class='sdata'>janapade</span> <span class='sdata'>na gadaḥ padamādadhau</span> &nbsp;<span class='ls'>R. 9. 4</span>&nbsp;; &nbsp;<span class='ls'>Bg. 5. 10</span>&nbsp;; <span class='sdata'>duṣyaṃtenāhitaṃ tejaḥ</span> &nbsp;<span class='ls'>Ś. 4. 3</span>&nbsp;; <span class='sdata'>āhito</span> <span class='sdata'>jayaviparyayopi me</span> &nbsp;<span class='ls'>R. 11. 86</span>&nbsp; inflicted on me; <span class='ls' title='R.'>19. 26</span>&nbsp;; <span class='sdata'>saṃbhṛte śikhini gūḍhamādadhuḥ</span> <span class='ls' title='R.'>19. 54</span>&nbsp; consigned to the flames, burnt; <span class='sdata'>dhairyaṃ cādhiṣatādhikaṃ</span> &nbsp;<span class='ls'>Bk. 7. 102</span>&nbsp; plucked up greater courage. <div style='margin-top:0.6em;'></div></div><strong>2</strong> To apply, propose, fix upon, direct towards; <span class='sdata'>pratipātramādhīyatāṃ yatnaḥ</span> &nbsp;<span class='ls'>Ś. 1</span>&nbsp;; <span class='sdata'>mayyeva mana</span> <span class='sdata'>ādhatsta</span> &nbsp;<span class='ls'>Bg. 12. 8</span>&nbsp;; <span class='sdata'>gamane matimādhatta</span> &nbsp;<span class='ls'>Rām.</span>&nbsp;; &nbsp;<span class='ls'>Ś. 2. 3</span>&nbsp;; <span class='sdata'>ādhīyatāṃ dhairye dharme ca</span> <span class='sdata'>dhīḥ</span> &nbsp;<span class='ls'>K. 63</span>&nbsp; direct; <span class='sdata'>sarvakāryeṣvāhitamatiḥ</span> &nbsp;<span class='ls'>K. 56.</span>&nbsp; <div style='margin-top:0.6em;'></div></div><strong>3</strong> To appropriate to oneself, hold, possess, take, carry, have, bear; <span class='sdata'>bhūyo babhau darpaṇamādadhānāṃ</span> <br/>(<span title='Page 0239-a' style='border-bottom: 1px dotted #000; text-decoration: none;'>pb</span>) &nbsp;<span class='ls'>Ku. 7. 26</span>&nbsp;; <span class='sdata'>ādhatte kanakamayātapatralakṣmīṃ</span> &nbsp;<span class='ls'>Ki. 5. 39</span>&nbsp; takes or assumes; <span class='sdata'>garmamādhatta</span> <span class='sdata'>rājñī</span> &nbsp;<span class='ls'>R. 2. 75</span>&nbsp;, <span class='ls' title='R.'>5. 57</span>&nbsp;; <span class='sdata'>āhitakrodhā</span> &nbsp;<span class='ls'>Amaru. 18.</span>&nbsp; <div style='margin-top:0.6em;'></div></div><strong>4</strong> To bear up, uphold, support; <span class='sdata'>śeṣaḥ sadaivāhitabhūmibhāraḥ</span> &nbsp;<span class='ls'>Ś. 5. 4.</span>&nbsp; <div style='margin-top:0.6em;'></div></div><strong>5</strong> To cause, produce, create, rouse, excite (fear, wonder &c.); <span class='sdata'>chāyāścaraṃti bahudhā bhayamādadhānāḥ</span> &nbsp;<span class='ls'>Ś. 3. 27</span>&nbsp;; &nbsp;<span class='ls'>Ki. 4. 12</span>&nbsp;, <span class='ls' title='Ki.'>6. 19</span>&nbsp;, <span class='ls' title='Ki.'>8. 46</span>&nbsp;, <span class='ls' title='Ki. 8.'>57</span>&nbsp;; &nbsp;<span class='ls'>Ku. 6. 20</span>&nbsp;; &nbsp;<span class='ls'>Bk. 2. 8</span>&nbsp;; <span class='sdata'>vismayaṃ</span> &nbsp;<span class='ls'>M. 5. 17</span>&nbsp;; &nbsp;<span class='ls'>K. 246</span>&nbsp;; <span class='sdata'>navarasarucirāṃ</span> <span class='sdata'>nirmitimādadhatī bhāratī</span> &nbsp;<span class='ls'>K. P. 1</span>&nbsp;; to put in, infuse; &nbsp;<span class='ls'>Śi. 2. 76.</span>&nbsp; <div style='margin-top:0.6em;'></div></div><strong>6</strong> To supply, give, impart (with <span>dat.</span>, <span>gen.</span> or loc); <span class='sdata'>śuddhimādadhānā</span> &nbsp;<span class='ls'>R. 1. 85</span>&nbsp;; <span class='sdata'>iṃdra</span> <span class='sdata'>trailokyamādhāya</span> &nbsp;<span class='ls'>Mb.</span>&nbsp; <div style='margin-top:0.6em;'></div></div><strong>7</strong> To appoint; <span class='sdata'>tameva cādhāya vivāhasākṣye</span> &nbsp;<span class='ls'>R. 7. 20.</span>&nbsp; <div style='margin-top:0.6em;'></div></div><strong>8</strong> To consecrate (as fire); <span class='sdata'>tatrāgnimādhāya samitsamiddhaṃ</span> &nbsp;<span class='ls'>Ku. 1. 57.</span>&nbsp; <div style='margin-top:0.6em;'></div></div><strong>9</strong> To perform, practise (as a vow &c.).","evidence":{"band":2,"band_label":"frequent -- learn early","rank_all":1010,"count_all":704,"first_era":"Vedic","genre":null,"example":{"sa":"ādadhe","ru":"вложила","work":"01_atharvaveda","passage":"28.3","kind":"translation","source":"corpus_lexicon.jsonl (pwg_ru Phase 4, SanskritLexicography/RussianTranslation)"},"badges":[{"field":"band","value":2,"label":"frequent -- learn early","source":"kosha frequency layer, rank_all (DCS archive.sqlite M9 via VisualDCS)"},{"field":"count_all","value":704,"label":"704 attestations in DCS","source":"DCS archive.sqlite M9 (VisualDCS)"},{"field":"first_era","value":"Vedic","label":"first attested: Vedic","source":"DCS archive.sqlite M9 (VisualDCS)"},{"field":"genre","value":null,"label":"genre sketch not derivable from current DCS extraction (only a chronological period vector is stored, no per-genre breakdown)","source":"n/a -- gap documented, not fabricated (see app/evidence.py)"}]}}]}