{"data_version":"0.1.0-dev","query":{"key":"Salyaparvan","in":"slp1","out":"iast","dicts":["mw","pwg","ap90"]},"results":[{"dict":"mw","L":"214152","sense_ids":["mw.214152.1@0.1.0-dev"],"scan_url":"https://sanskrit-lexicon.uni-koeln.de/scans/MWScan/2020/web/webtc/servepdf.php?page=1059","headword":"śalyaparvan","rendered_html":"<span class='sdata'>śalya—parvan</span> <strong>n.</strong> <span>N.</span> of the ninth book of the Mahā-bhārata, (this book describes how, on the death of Karṇa, Śalya, king of Madra, was appointed to the command of the Kuru army, and how a combat with maces took place between Śalya and Bhīma, and another great battle between Śalya and Yudhiṣṭhira, in which the former was at last killed).","evidence":{"band":4,"band_label":"attested -- look up","rank_all":26474,"count_all":4,"first_era":null,"genre":null,"example":{"sa":"śalyaparva","ru":"Шалье","work":"01_mahabharata-adiparva","passage":"1.2.54-60","kind":"translation","source":"corpus_lexicon.jsonl (pwg_ru Phase 4, SanskritLexicography/RussianTranslation)"},"badges":[{"field":"band","value":4,"label":"attested -- look up","source":"kosha frequency layer, rank_all (DCS archive.sqlite M9 via VisualDCS)"},{"field":"count_all","value":4,"label":"4 attestations in DCS","source":"DCS archive.sqlite M9 (VisualDCS)"},{"field":"first_era","value":null,"label":"no attestation data","source":"n/a -- gap documented, not fabricated (see app/evidence.py)"},{"field":"genre","value":null,"label":"genre sketch not derivable from current DCS extraction (only a chronological period vector is stored, no per-genre breakdown)","source":"n/a -- gap documented, not fabricated (see app/evidence.py)"}]}}]}