{"data_version":"0.1.0-dev","query":{"key":"aDastAt","in":"slp1","out":"iast","dicts":["mw","pwg","ap90"]},"results":[{"dict":"mw","L":"4111","sense_ids":["mw.4111.1@0.1.0-dev"],"scan_url":"https://sanskrit-lexicon.uni-koeln.de/scans/MWScan/2020/web/webtc/servepdf.php?page=20","headword":"adhastāt","rendered_html":"<span class='sdata'>adhastāt</span> <strong>ind.</strong> = <span class='sdata'>adhas</span>, <span>q.v.</span>","evidence":{"band":3,"band_label":"common -- recognise","rank_all":2455,"count_all":252,"first_era":"Vedic","genre":null,"example":{"sa":"adhastāt","ru":"под","work":"02_ramayana-ayodhyakanda","passage":"9.42","kind":"translation","source":"corpus_lexicon.jsonl (pwg_ru Phase 4, SanskritLexicography/RussianTranslation)"},"badges":[{"field":"band","value":3,"label":"common -- recognise","source":"kosha frequency layer, rank_all (DCS archive.sqlite M9 via VisualDCS)"},{"field":"count_all","value":252,"label":"252 attestations in DCS","source":"DCS archive.sqlite M9 (VisualDCS)"},{"field":"first_era","value":"Vedic","label":"first attested: Vedic","source":"DCS archive.sqlite M9 (VisualDCS)"},{"field":"genre","value":null,"label":"genre sketch not derivable from current DCS extraction (only a chronological period vector is stored, no per-genre breakdown)","source":"n/a -- gap documented, not fabricated (see app/evidence.py)"}]}},{"dict":"pwg","L":"1907","sense_ids":["pwg.1907.1@0.1.0-dev","pwg.1907.2@0.1.0-dev","pwg.1907.3@0.1.0-dev","pwg.1907.4@0.1.0-dev","pwg.1907.5@0.1.0-dev","pwg.1907.6@0.1.0-dev","pwg.1907.7@0.1.0-dev","pwg.1907.8@0.1.0-dev","pwg.1907.9@0.1.0-dev","pwg.1907.10@0.1.0-dev","pwg.1907.11@0.1.0-dev","pwg.1907.12@0.1.0-dev","pwg.1907.13@0.1.0-dev"],"scan_url":"https://sanskrit-lexicon.uni-koeln.de/scans/PWGScan/2020/web/webtc/servepdf.php?page=141","headword":"adhastāt","rendered_html":"<span class='sdata'>adhastāt</span> oder <span class='sdata'>adhastāt</span> (von <span class='sdata'>adhas</span>) &nbsp;<span class='ls'>P. 5,3,27</span>&nbsp;. <span class='ls' title='P. 5,3,'>40</span>&nbsp;. <div style='padding-left:1.0em;'> 1〉 <strong>adv.</strong> </div><div style='padding-left:2.0em;'> a〉 <i>unten</i>: <span class='sdata'>vṛścemadhastādvi rujā sahasva</span> &nbsp;<span class='ls'>ṚV. 3,30,16</span>&nbsp;. &nbsp;<span class='ls'>AV. 4,40,5</span>&nbsp;. <span class='sdata'>sa evādhastātsa upariṣṭāt</span> &nbsp;<span class='ls'>CHĀND. UP. 7,25,1</span>&nbsp;. &nbsp;<span class='ls'>AIT. UP. 1,2</span>&nbsp;. &nbsp;<span class='ls'>R. 2,9,33</span>&nbsp;. <span class='ls' title='R.'>4,28,26</span>&nbsp;. &nbsp;<span class='ls'>AK. 2,2,13</span>&nbsp;. <span class='ls' title='AK.'>3,4,191</span>&nbsp;. &nbsp;<span class='ls'>H. 1526</span>&nbsp;. <i>auf dem Erdboden</i>: <span class='sdata'>adhastācchiṃśapāyāṃ tu adhyāste</span> &nbsp;<span class='ls'>R. 5,57,6</span>&nbsp;. vom <i>pudendum muliebre</i> &nbsp;<span class='ls'>TRIK. 2,6,21</span>&nbsp; (<span class='sdata'>adhasthāt</span>); <span>vgl.</span> <span class='sdata'>adhastādramaṇīyam</span> beim <span>Sch.</span> zu &nbsp;<span class='ls'>P. 5,3,27</span>&nbsp;. </div><div style='padding-left:2.0em;'>— b〉 <i>nach unten hin</i>: <span class='sdata'>adhastānnopadadhyācca (agnim)</span> &nbsp;<span class='ls'>M. 4,54</span>&nbsp; (&nbsp;<span class='ls'>KULL.</span>&nbsp;: <span class='sdata'>khaṭvādibhyo 'dhastādaṅgāraśakaṭyādikaṃ na kuryāt</span>). <i>in die Hölle</i>: <span class='sdata'>tathā nimajjato 'dhastādajñau</span> &nbsp;<span class='ls'>M. 4,194</span>&nbsp;. <span class='sdata'>dharmeṇa gamanamūrdhvaṃ gamanamadhastādbhavatyadharmeṇa</span> &nbsp;<span class='ls'>SĀṂKHYAK. 44</span>&nbsp;. </div><div style='padding-left:2.0em;'>— c〉 <i>von unten her</i>: <span class='sdata'>adhastādiva hi śreyasa upacāraḥ</span> &nbsp;<span class='ls'>ŚAT. BR. 1,1,1,11</span>&nbsp;. <span class='sdata'>nenno 'dhastānnāṣṭrā rakṣāṃsyupottiṣṭhān</span> <span class='ls' title='ŚAT. BR. 1,'>2,1,6</span>&nbsp;. <span class='sdata'>yāmadhastādupacarasi</span> <span class='ls' title='ŚAT. BR. 1,'>9,1,8</span>&nbsp;. <span class='sdata'>adhastādāgataḥ</span> &nbsp;<span class='ls'>P. 5,3,27</span>&nbsp;, <span>Sch.</span> </div><div style='padding-left:2.0em;'>— d〉 <i>in Unterwürfigkeit</i>: <span class='sdata'>tasmātkṣatrātparaṃ nāsti tasmādbrāhmaṇaḥ kṣatriyamadhastādupāste</span> &nbsp;<span class='ls'>ŚAT. BR. 14,4,2,23</span>&nbsp;. = &nbsp;<span class='ls'>BṚH. ĀR. UP. 1,4,11</span>&nbsp;. </div><div style='padding-left:2.0em;'>— e〉 <i>nachher, darnach</i> (<span>Gegens.</span> <span class='sdata'>upariṣṭāt</span>) &nbsp;<span class='ls'>YĀJÑ. 1,106</span>&nbsp;. </div><div style='padding-left:1.0em;'>— 2〉 <span>praep.</span> <i>unter, unterhalb</i> (auf die Frage <i>wo</i> oder <i>wohin</i>). </div><div style='padding-left:2.0em;'> a〉 mit dem <span>gen.</span>: <span class='sdata'>so 'dhastācchakaṭasya — -upopaviveśa</span> &nbsp;<span class='ls'>CHĀND. UP. 4,1,8</span>&nbsp;. &nbsp;<span class='ls'>PAÑCAT. 171,12</span>&nbsp;. <span class='ls' title='PAÑCAT.'>209,9</span>&nbsp;. <span class='ls' title='PAÑCAT.'>252,11</span>&nbsp;. &nbsp;<span class='ls'>HIT. 111,15</span>&nbsp;. </div><div style='padding-left:2.0em;'>— b〉 mit dem <span>abl.</span> &nbsp;<span class='ls'>KULL.</span>&nbsp;_zu_&nbsp;<span class='ls'>M. 4,54</span>&nbsp; (<span>s.</span> oben <span title='und' style='border-bottom: 1px dotted #000; text-decoration: none;'>u.</span> 1,b.). </div><div style='padding-left:2.0em;'>— c〉 nicht zu entscheiden, ob mit dem <span>gen.</span> oder <span>abl.</span>: <span class='sdata'>taroradhastādupaviṣṭaḥ</span> &nbsp;<span class='ls'>HIT. 43,18</span>&nbsp;. <span class='sdata'>gireradhastāt</span> &nbsp;<span class='ls'>H. 1526</span>&nbsp;, <span>Sch.</span> </div><div style='padding-left:2.0em;'>— d〉 am Ende eines <span>comp.</span>: <span class='sdata'>nābhyadhastāt</span> &nbsp;<span class='ls'>SUŚR. 2,199,2</span>&nbsp;. <span class='sdata'>vṛkṣacchāyādhastāt</span> &nbsp;<span class='ls'>PAÑCAT. 141,20</span>&nbsp;. </div><div style='padding-left:0.1em;'>— <span>Vgl.</span> <span class='sdata'>adhas</span>.</div>","evidence":{"band":3,"band_label":"common -- recognise","rank_all":2455,"count_all":252,"first_era":"Vedic","genre":null,"example":{"sa":"adhastāt","ru":"под","work":"02_ramayana-ayodhyakanda","passage":"9.42","kind":"translation","source":"corpus_lexicon.jsonl (pwg_ru Phase 4, SanskritLexicography/RussianTranslation)"},"badges":[{"field":"band","value":3,"label":"common -- recognise","source":"kosha frequency layer, rank_all (DCS archive.sqlite M9 via VisualDCS)"},{"field":"count_all","value":252,"label":"252 attestations in DCS","source":"DCS archive.sqlite M9 (VisualDCS)"},{"field":"first_era","value":"Vedic","label":"first attested: Vedic","source":"DCS archive.sqlite M9 (VisualDCS)"},{"field":"genre","value":null,"label":"genre sketch not derivable from current DCS extraction (only a chronological period vector is stored, no per-genre breakdown)","source":"n/a -- gap documented, not fabricated (see app/evidence.py)"}]}},{"dict":"ap90","L":"922","sense_ids":["ap90.922.1@0.1.0-dev"],"scan_url":"https://sanskrit-lexicon.uni-koeln.de/scans/AP90Scan/2020/web/webtc/servepdf.php?page=45","headword":"adhastāt","rendered_html":"<span class='sdata'>adhastāt</span> <i><span>adv.</span></i> or <i><span>prep.</span></i> [<span class='sdata'>adhara-astāti, adh ādeśaḥ</span> &nbsp;<span class='ls'>P. V. 3. 39-40</span>&nbsp;.] Down, below, under, beneath, under-neath &c. (with <span>gen.</span>), See <span class='sdata'>adhaḥ; adhastānnopadadhyācca</span> &nbsp;<span class='ls'>Ms. 4. 54</span>&nbsp;; <span class='sdata'>dharmeṇa gamanamūrdhvaṃ gamanamadhastādbhavatyadharmeṇa</span> &nbsp;<span class='ls'>Sāṅ. K.</span>&nbsp;; <span class='sdata'>˚tādāgataḥ</span> &nbsp;<span class='ls'>Pt. 3.</span>&nbsp;; <span class='sdata'>tasyādhastādvayamapi ratāsteṣu parṇoṭajeṣu</span> &nbsp;<span class='ls'>U. 2. 25</span>&nbsp;; <span class='sdata'>yasya sarvamevādhastādgataṃ</span> &nbsp;<span class='ls'>K. 289</span>&nbsp; gone to hell.","evidence":{"band":3,"band_label":"common -- recognise","rank_all":2455,"count_all":252,"first_era":"Vedic","genre":null,"example":{"sa":"adhastāt","ru":"под","work":"02_ramayana-ayodhyakanda","passage":"9.42","kind":"translation","source":"corpus_lexicon.jsonl (pwg_ru Phase 4, SanskritLexicography/RussianTranslation)"},"badges":[{"field":"band","value":3,"label":"common -- recognise","source":"kosha frequency layer, rank_all (DCS archive.sqlite M9 via VisualDCS)"},{"field":"count_all","value":252,"label":"252 attestations in DCS","source":"DCS archive.sqlite M9 (VisualDCS)"},{"field":"first_era","value":"Vedic","label":"first attested: Vedic","source":"DCS archive.sqlite M9 (VisualDCS)"},{"field":"genre","value":null,"label":"genre sketch not derivable from current DCS extraction (only a chronological period vector is stored, no per-genre breakdown)","source":"n/a -- gap documented, not fabricated (see app/evidence.py)"}]}}]}