{"data_version":"0.1.0-dev","query":{"key":"aviSrAnta","in":"slp1","out":"iast","dicts":["mw","pwg","ap90"]},"results":[{"dict":"mw","L":"19050","sense_ids":["mw.19050.1@0.1.0-dev"],"scan_url":"https://sanskrit-lexicon.uni-koeln.de/scans/MWScan/2020/web/webtc/servepdf.php?page=110","headword":"aviśrānta","rendered_html":"<span class='sdata'>a-viśrānta</span> <strong>mfn.</strong> unwearied","evidence":{"band":4,"band_label":"attested -- look up","rank_all":15149,"count_all":13,"first_era":null,"genre":null,"example":{"sa":"aviśrānta","ru":"с легкостью","work":"hatha-yoga-pradipika","passage":"3.56","kind":"translation","source":"corpus_lexicon.jsonl (pwg_ru Phase 4, SanskritLexicography/RussianTranslation)"},"badges":[{"field":"band","value":4,"label":"attested -- look up","source":"kosha frequency layer, rank_all (DCS archive.sqlite M9 via VisualDCS)"},{"field":"count_all","value":13,"label":"13 attestations in DCS","source":"DCS archive.sqlite M9 (VisualDCS)"},{"field":"first_era","value":null,"label":"no attestation data","source":"n/a -- gap documented, not fabricated (see app/evidence.py)"},{"field":"genre","value":null,"label":"genre sketch not derivable from current DCS extraction (only a chronological period vector is stored, no per-genre breakdown)","source":"n/a -- gap documented, not fabricated (see app/evidence.py)"}]}},{"dict":"mw","L":"19051","sense_ids":["mw.19051.1@0.1.0-dev"],"scan_url":"https://sanskrit-lexicon.uni-koeln.de/scans/MWScan/2020/web/webtc/servepdf.php?page=110","headword":"aviśrānta","rendered_html":"incessant, &nbsp;<span class='ls'>Śak.</span>&nbsp;","evidence":{"band":4,"band_label":"attested -- look up","rank_all":15149,"count_all":13,"first_era":null,"genre":null,"example":{"sa":"aviśrānta","ru":"с легкостью","work":"hatha-yoga-pradipika","passage":"3.56","kind":"translation","source":"corpus_lexicon.jsonl (pwg_ru Phase 4, SanskritLexicography/RussianTranslation)"},"badges":[{"field":"band","value":4,"label":"attested -- look up","source":"kosha frequency layer, rank_all (DCS archive.sqlite M9 via VisualDCS)"},{"field":"count_all","value":13,"label":"13 attestations in DCS","source":"DCS archive.sqlite M9 (VisualDCS)"},{"field":"first_era","value":null,"label":"no attestation data","source":"n/a -- gap documented, not fabricated (see app/evidence.py)"},{"field":"genre","value":null,"label":"genre sketch not derivable from current DCS extraction (only a chronological period vector is stored, no per-genre breakdown)","source":"n/a -- gap documented, not fabricated (see app/evidence.py)"}]}}]}