{"data_version":"0.1.0-dev","query":{"key":"mlA","in":"slp1","out":"iast","dicts":["mw","pwg","ap90"]},"results":[{"dict":"pwg","L":"62381","sense_ids":["pwg.62381.1@0.1.0-dev","pwg.62381.2@0.1.0-dev","pwg.62381.3@0.1.0-dev","pwg.62381.4@0.1.0-dev","pwg.62381.5@0.1.0-dev","pwg.62381.6@0.1.0-dev","pwg.62381.7@0.1.0-dev","pwg.62381.8@0.1.0-dev","pwg.62381.9@0.1.0-dev"],"scan_url":"https://sanskrit-lexicon.uni-koeln.de/scans/PWGScan/2020/web/webtc/servepdf.php?page=932","headword":"mlā","rendered_html":"<span class='sdata'>mlā</span> , <span class='sdata'>mlāyati</span> &nbsp;<span class='ls'>DHĀTUP. 22,8</span>&nbsp; (<span class='sdata'>gātravināme, kāntisaṃkṣaye</span>). <span class='sdata'>mlāyate</span> &nbsp;<span class='ls'>MBH. 12,6831</span>&nbsp;. &nbsp;<span class='ls'>Spr. 1143</span>&nbsp;. <span class='sdata'>mlānti</span> &nbsp;<span class='ls'>MBH. 3,15683</span>&nbsp;. <span class='sdata'>malau, mamle</span> (&nbsp;<span class='ls'>P. 6,1,45</span>&nbsp;, <span>Sch.</span>), <span class='sdata'>amlāsīt; mlāyāt</span> und <span class='sdata'>mleyāt</span> (<span>vgl.</span> &nbsp;<span class='ls'>P. 6,4,68</span>&nbsp;); <span>partic.</span> <span class='sdata'>mlāta</span> (in der älteren Sprache) und <span class='sdata'>mlāna</span> (<span>vgl.</span> &nbsp;<span class='ls'>P. 8,2,43</span>&nbsp;). <i>welken</i>: <span class='sdata'>mlāyantyoṣadhayaḥ</span> &nbsp;<span class='ls'>ŚAT. BR. 1,5,4,5</span>&nbsp;. <span class='ls' title='ŚAT. BR.'>3,6,1,10</span>&nbsp;. <span class='ls' title='ŚAT. BR.'>8,1,4,1</span>&nbsp;. <span class='ls' title='ŚAT. BR. 8,'>7,2,14</span>&nbsp;. &nbsp;<span class='ls'>MBH. 3,15455</span>&nbsp;. &nbsp;<span class='ls'>R. 3,77,24</span>&nbsp;. <span class='sdata'>ūṣmato mlāyate parṇaṃ tvakphalaṃ puṣpameva ca . glāyate</span> (<span class='sdata'>mlāyate</span> &nbsp;<span class='ls'>ed. Bomb.</span>&nbsp;) <span class='sdata'>śīryate cāpi</span> &nbsp;<span class='ls'>MBH. 12,6831</span>&nbsp;. <span class='sdata'>vṛkṣāśca na mlānti tathaiva bhagnāḥ</span> <span class='ls' title='MBH.'>3,15683</span>&nbsp;. <span class='sdata'>mamlau</span> &nbsp;<span class='ls'>RĀJA-TAR. 1,62</span>&nbsp;. <span class='sdata'>mlānasraj</span> <i>verwelkt, welk</i> &nbsp;<span class='ls'>MBH. 3,2215</span>&nbsp;. &nbsp;<span class='ls'>Spr. 440</span>&nbsp;. &nbsp;<span class='ls'>UTTARARĀMAC. 17,9</span>&nbsp;. &nbsp;<span class='ls'>LA. (II) 91,22</span>&nbsp;. <span class='sdata'>amlānānyapi tatrāsankusumāni</span> &nbsp;<span class='ls'>MBH. 13,2357</span>&nbsp;. &nbsp;<span class='ls'>HARIV. 7008</span>&nbsp;. &nbsp;<span class='ls'>KATHĀS. 13,84</span>&nbsp;. &nbsp;<span class='ls'>PAÑCAR. 1,7,34</span>&nbsp;. <span class='ls' title='PAÑCAR. 1,'>11,37</span>&nbsp;. [Page5-0933] vom Gesicht, das durch Krankheit, Sorgen, Leidenschaften <i>ein welkes, leidendes, verstelltes Ansehen erhält</i>: <span class='sdata'>mlāyadvaktra ivāvādīt</span> &nbsp;<span class='ls'>RĀJA-TAR. 4,95</span>&nbsp;. <span class='sdata'>mlāyateṣanmukhena</span> &nbsp;<span class='ls'>BHĀG. P. 1,16,20</span>&nbsp;. <span class='sdata'>himāhatamivāmbhojaṃ palitamlānamānanam</span> &nbsp;<span class='ls'>KATHĀS. 40,45</span>&nbsp;. <span class='ls' title='KATHĀS.'>71,64</span>&nbsp;. <span class='sdata'>vaktramādhimlānam</span> &nbsp;<span class='ls'>BHĀG. P. 6,15,9</span>&nbsp;. &nbsp;<span class='ls'>Spr. 5293</span>&nbsp;. <i>erschlaffen, schwach werden</i> überh: <span class='sdata'>pādau te 'mlāsyatām</span> &nbsp;<span class='ls'>ŚAT. BR. 10,6,1,4</span>&nbsp;. <span class='sdata'>babhramuścaskhaluścānye peturmamlustathāpare</span> &nbsp;<span class='ls'>MBH. 7,4568</span>&nbsp;. <span class='sdata'>pathi — mamlaturna</span> &nbsp;<span class='ls'>RAGH. 11,9</span>&nbsp;. &nbsp;<span class='ls'>BHAṬṬ. 14,6</span>&nbsp;. <span class='sdata'>mlānakṣīṇā</span> &nbsp;<span class='ls'>RĀJA-TAR. 5,431</span>&nbsp;. &nbsp;<span class='ls'>MĀRK. P. 62,16</span>&nbsp;. &nbsp;<span class='ls'>Spr. 440</span>&nbsp;. <span class='sdata'>amlāno balavāñchūraśchāyevānugataḥ sadā</span> &nbsp;<span class='ls'>MBH. 4,126</span>&nbsp;. <span class='sdata'>asminvivāhe mā mlāsīḥ</span> so <span>v. a.</span> <i>den Kopf hängen lassen</i> <span class='ls' title='MBH.'>1,3391</span>&nbsp;. <span class='sdata'>mlānendriya</span> &nbsp;<span class='ls'>Spr. 2012</span>&nbsp;. <span class='sdata'>mlāyate me mano hīdaṃ mukhaṃ ca pariśuṣyati</span> &nbsp;<span class='ls'>MBH. 15,120</span>&nbsp;. <span class='sdata'>amlānamanasaṃ yudhi</span> <span class='ls' title='MBH.'>7,350</span>&nbsp;. <span class='sdata'>ūhuramlānamanasaścekitānaṃ hayottamāḥ</span> <span class='ls' title='MBH. 7,'>994</span>&nbsp;. <i>dahinschwinden</i>: <span class='sdata'>bhrātṛvyo mlāyati</span> &nbsp;<span class='ls'>ŚAT. BR. 10,6,2,10</span>&nbsp;. <span class='sdata'>mlāyati śrīḥ kulastrīva gṛhe bandhakyadhiṣṭhite</span> &nbsp;<span class='ls'>KATHĀS. 52,317</span>&nbsp;. <span class='sdata'>amlānalakṣmyā vanamālayā</span> &nbsp;<span class='ls'>BHĀG. P. 2,2,10</span>&nbsp;. <span class='sdata'>amlānamukhacchāya</span> (<span class='sdata'>amlāna</span> gehört zu <span class='sdata'>mukhacchāyā</span>) &nbsp;<span class='ls'>KATHĀS. 39,49</span>&nbsp;. <span class='sdata'>mlānavrīḍa</span> <span>v. l.</span> für <span class='sdata'>vītavrīḍa</span> &nbsp;<span class='ls'>Spr. 197</span>&nbsp;. <span class='sdata'>amlānamānā</span> <span class='ls' title='Spr.'>3744</span>&nbsp;. — <span class='sdata'>mlāta</span> <i>durch Gerben weich geworden</i>: <span class='sdata'>carmāṇi</span> &nbsp;<span class='ls'>VĀLAKH. 7,3</span>&nbsp;; <span>vgl.</span> <span class='sdata'>carmamna</span>. <span class='sdata'>mlāna</span> <i>schmutzig</i> (<span>vgl.</span> <span class='sdata'>mala</span>) &nbsp;<span class='ls'>H. 1435</span>&nbsp;. &nbsp;<span class='ls'>HALĀY. 4,42</span>&nbsp;. <span class='sdata'>mlānāṅgī</span> <i>eine Frau während der Regeln</i> &nbsp;<span class='ls'>TRIK. 2,6,6, Ind.</span>&nbsp; <i>schwarz, dunkelfarbig</i>: <span class='sdata'>dhanamadamasīmlānavaktra</span> (<span class='sdata'>mlāna</span> = <span class='sdata'>śuṣka</span> <span>Schol.</span>) &nbsp;<span class='ls'>PRAB. 92,18</span>&nbsp;. <span class='sdata'>mānamlānamasī</span> &nbsp;<span class='ls'>Spr. 3739</span>&nbsp;. <span>Vgl.</span> <span class='sdata'>amlātaka</span> und <span class='sdata'>amlāna; mlāna</span> <strong>n.</strong> <span>s.</span> besonders. <div style='padding-left:0.1em;'>— <span>caus.</span> <i>welk machen, die Spannkraft benehmen</i>: <span class='sdata'>aṅgaiṣā mlāpayāmasi</span> &nbsp;<span class='ls'>AV. 6,66,3</span>&nbsp;. <span class='sdata'>mlāpayāmi bhrajaḥ śibhram</span> <span class='ls' title='AV.'>7,90,1</span>&nbsp;. </div><div style='padding-left:0.1em;'>— <span class='sdata'>abhi</span> <span>s.</span> <span class='sdata'>anabhimlāta</span> und <span class='sdata'>anabhimlāna</span> (in den Nachträgen). </div><div style='padding-left:0.1em;'>— <span class='sdata'>ā</span>, <span>partic.</span> <span class='sdata'>āmlāna</span> <i>welk</i> oder <i>ein wenig</i> (<span class='sdata'>ā</span>) <i>welk</i>: <span class='sdata'>˚mukhāravinda</span> &nbsp;<span class='ls'>RAGH. 16,75</span>&nbsp;. </div><div style='padding-left:0.1em;'>— <span class='sdata'>pari</span> <i>verwelken, dahinwelken</i>: <span class='sdata'>vṛkṣāḥ parimlānāḥ</span> &nbsp;<span class='ls'>R. 2,59,8</span>&nbsp; (<span class='ls' title='R. 2,59,'>7 GORR.</span>&nbsp;). <span class='sdata'>parimlānāmbujamukhī</span> &nbsp;<span class='ls'>KATHĀS. 30,31</span>&nbsp;. <span class='sdata'>˚mukhāravindā</span> &nbsp;<span class='ls'>RAGH. 14,50</span>&nbsp;. &nbsp;<span class='ls'>BHĀG. P. 4,8,66</span>&nbsp;. <span class='sdata'>˚mukhaśrī</span> <span class='ls' title='BHĀG. P.'>8,7,7</span>&nbsp;. &nbsp;<span class='ls'>KUMĀRAS. 2,2</span>&nbsp;. <span class='sdata'>śrāntasya te kṣudhārtasya parimlānasya</span> <i>erschlafft</i> &nbsp;<span class='ls'>MBH. 3,2386</span>&nbsp;. <span class='sdata'>śīlaśaśinaḥ kāntiḥ parimlāyate</span> <i>schwindet dahin</i> &nbsp;<span class='ls'>Spr. 1144</span>&nbsp;. <span class='sdata'>parimlāne māne</span> <span class='ls' title='Spr.'>1720</span>&nbsp;. </div><div style='padding-left:0.1em;'>— <span>Vgl.</span> <span class='sdata'>aparimlāna, parimlāyin</span>. </div><div style='padding-left:0.1em;'>— <span class='sdata'>vipari</span>, <span>partic.</span> <span class='sdata'>˚mlāna</span> <i>vollkommen verwelkt</i> &nbsp;<span class='ls'>R. 4,15,34</span>&nbsp;. </div><div style='padding-left:0.1em;'>— <span class='sdata'>pra</span> <i>verwelken, welk werden</i> &nbsp;<span class='ls'>BHAṬṬ. 6,13</span>&nbsp;, <span>v. l.</span> <span class='sdata'>pramlānā iva ca srajaḥ</span> &nbsp;<span class='ls'>MBH. 8,859</span>&nbsp;. <span class='ls' title='MBH.'>11,717</span>&nbsp;. &nbsp;<span class='ls'>R. GORR. 2,57,5</span>&nbsp;. <span class='ls' title='R. GORR. 2,'>59,8</span>&nbsp;. <span class='ls' title='R. GORR. 2,'>73,18</span>&nbsp;. <span class='sdata'>˚bījāṅkura</span> &nbsp;<span class='ls'>RAGH. 7,24</span>&nbsp;. <span class='sdata'>˚bhāva</span> &nbsp;<span class='ls'>KĀM. NĪTIS. 7,21</span>&nbsp;. <span class='sdata'>pramlānībhū</span> &nbsp;<span class='ls'>PAÑCAR. 3,5,30</span>&nbsp;. <span class='sdata'>pramlānabadana</span> <i>das Gesicht verziehend</i> &nbsp;<span class='ls'>MBH. 7,5130</span>&nbsp;. <span class='sdata'>kṣutpramlānaśarīra</span> <i>ausgemergelt</i> &nbsp;<span class='ls'>VARĀH. BṚH. S. 3,13</span>&nbsp;. <i>welk werden, dahinschwinden</i> von einem Mädchen &nbsp;<span class='ls'>Spr. 1971</span>&nbsp;. <span class='sdata'>pramlāna</span> <i>schmutzig, verunreinigt</i>: <span class='sdata'>dantino madajalapramlānagaṇḍasthalāḥ</span> <span class='ls' title='Spr.'>5155</span>&nbsp;. </div><div style='padding-left:0.1em;'>— <span class='sdata'>vi</span> <i>welk werden</i>: <span class='sdata'>vimlāna</span> <i>verwelkt</i> und zugleich <i>um sein Ansehen gekommen</i> &nbsp;<span class='ls'>KUSUM. 1,8</span>&nbsp;. <i>erschlaffen</i>: <span class='sdata'>pādau te vyamlāsyetām</span> &nbsp;<span class='ls'>CHĀND. UP. 5,17,2</span>&nbsp;. — <span>caus.</span> <i>welk machen</i>: <span class='sdata'>vidārikāṃ samabhyajya svinnāṃ vimlāpya lepayet</span> &nbsp;<span class='ls'>SUŚR. 2,118,10</span>&nbsp;.</div>","evidence":{"band":3,"band_label":"common -- recognise","rank_all":5660,"count_all":77,"first_era":"Vedic","genre":null,"example":{"sa":"mamlur","ru":"поблекли","work":"01_mahabharata-adiparva","passage":"1.26.27-34","kind":"translation","source":"corpus_lexicon.jsonl (pwg_ru Phase 4, SanskritLexicography/RussianTranslation)"},"badges":[{"field":"band","value":3,"label":"common -- recognise","source":"kosha frequency layer, rank_all (DCS archive.sqlite M9 via VisualDCS)"},{"field":"count_all","value":77,"label":"77 attestations in DCS","source":"DCS archive.sqlite M9 (VisualDCS)"},{"field":"first_era","value":"Vedic","label":"first attested: Vedic","source":"DCS archive.sqlite M9 (VisualDCS)"},{"field":"genre","value":null,"label":"genre sketch not derivable from current DCS extraction (only a chronological period vector is stored, no per-genre breakdown)","source":"n/a -- gap documented, not fabricated (see app/evidence.py)"}]}},{"dict":"pwg","L":"80798","sense_ids":["pwg.80798.1@0.1.0-dev"],"scan_url":"https://sanskrit-lexicon.uni-koeln.de/scans/PWGScan/2020/web/webtc/servepdf.php?page=1678","headword":"mlā","rendered_html":"<span class='sdata'>mlā</span> <span>caus.</span> <span>vgl.</span> <span style='color: brown;' title='Greek language'>βλάπτω</span>.","evidence":{"band":3,"band_label":"common -- recognise","rank_all":5660,"count_all":77,"first_era":"Vedic","genre":null,"example":{"sa":"mamlur","ru":"поблекли","work":"01_mahabharata-adiparva","passage":"1.26.27-34","kind":"translation","source":"corpus_lexicon.jsonl (pwg_ru Phase 4, SanskritLexicography/RussianTranslation)"},"badges":[{"field":"band","value":3,"label":"common -- recognise","source":"kosha frequency layer, rank_all (DCS archive.sqlite M9 via VisualDCS)"},{"field":"count_all","value":77,"label":"77 attestations in DCS","source":"DCS archive.sqlite M9 (VisualDCS)"},{"field":"first_era","value":"Vedic","label":"first attested: Vedic","source":"DCS archive.sqlite M9 (VisualDCS)"},{"field":"genre","value":null,"label":"genre sketch not derivable from current DCS extraction (only a chronological period vector is stored, no per-genre breakdown)","source":"n/a -- gap documented, not fabricated (see app/evidence.py)"}]}}]}