{"data_version":"0.1.0-dev","query":{"key":"niyuD","in":"slp1","out":"iast","dicts":["mw","pwg","ap90"]},"results":[{"dict":"mw","L":"109248","sense_ids":["mw.109248.1@0.1.0-dev"],"scan_url":"https://sanskrit-lexicon.uni-koeln.de/scans/MWScan/2020/web/webtc/servepdf.php?page=552","headword":"niyudh","rendered_html":"<span class='sdata'>ni-√yudh</span> <span>Ā.</span> <span class='sdata'>-yudhyate</span> (rarely <span class='sdata'>˚ti</span>), to fight, &nbsp;<span class='ls'>MBh.</span>&nbsp;; &nbsp;<span class='ls'>Hariv.</span>&nbsp; &c.","evidence":{"band":4,"band_label":"attested -- look up","rank_all":30141,"count_all":3,"first_era":null,"genre":null,"example":{"sa":"niyotsyanti","ru":"захотят состязаться","work":"04_mahabharata-virataparva","passage":"4.2.1-8","kind":"translation","source":"corpus_lexicon.jsonl (pwg_ru Phase 4, SanskritLexicography/RussianTranslation)"},"badges":[{"field":"band","value":4,"label":"attested -- look up","source":"kosha frequency layer, rank_all (DCS archive.sqlite M9 via VisualDCS)"},{"field":"count_all","value":3,"label":"3 attestations in DCS","source":"DCS archive.sqlite M9 (VisualDCS)"},{"field":"first_era","value":null,"label":"no attestation data","source":"n/a -- gap documented, not fabricated (see app/evidence.py)"},{"field":"genre","value":null,"label":"genre sketch not derivable from current DCS extraction (only a chronological period vector is stored, no per-genre breakdown)","source":"n/a -- gap documented, not fabricated (see app/evidence.py)"}]}}]}