{"data_version":"0.1.0-dev","query":{"key":"vicar","in":"slp1","out":"iast","dicts":["mw","pwg","ap90"]},"results":[{"dict":"mw","L":"194708","sense_ids":["mw.194708.1@0.1.0-dev","mw.194708.2@0.1.0-dev","mw.194708.3@0.1.0-dev","mw.194708.4@0.1.0-dev","mw.194708.5@0.1.0-dev","mw.194708.6@0.1.0-dev","mw.194708.7@0.1.0-dev","mw.194708.8@0.1.0-dev","mw.194708.9@0.1.0-dev","mw.194708.10@0.1.0-dev","mw.194708.11@0.1.0-dev","mw.194708.12@0.1.0-dev","mw.194708.13@0.1.0-dev","mw.194708.14@0.1.0-dev","mw.194708.15@0.1.0-dev","mw.194708.16@0.1.0-dev"],"scan_url":"https://sanskrit-lexicon.uni-koeln.de/scans/MWScan/2020/web/webtc/servepdf.php?page=958","headword":"vicar","rendered_html":"<span class='sdata'>vi-√car</span> <span>P.</span> <span class='sdata'>-carati</span>, to move in different directions, spread, expand, be diffused, &nbsp;<span class='ls'>RV.</span>&nbsp;; &nbsp;<span class='ls'>MBh.</span>&nbsp;; &nbsp;<span class='ls'>VarBṛS.</span>&nbsp;; <div style='margin-top:0.6em;'></div></div>to rove, ramble about or through, traverse, pervade, &nbsp;<span class='ls'>RV.</span>&nbsp; &c. &c.; <div style='margin-top:0.6em;'></div></div>to sally forth, march against, make an attack or assault, &nbsp;<span class='ls'>Mn.</span>&nbsp;; &nbsp;<span class='ls'>MBh.</span>&nbsp; &c.; <div style='margin-top:0.6em;'></div></div>to wander from the right path, go astray, be dissolute, &nbsp;<span class='ls'>Mn. ix, 20</span>&nbsp;; <div style='margin-top:0.6em;'></div></div>to commit a mistake or blunder (with words), &nbsp;<span class='ls'>BhP.</span>&nbsp;; <div style='margin-top:0.6em;'></div></div>to run out, come to an end, &nbsp;<span class='ls'>RV.</span>&nbsp;; <div style='margin-top:0.6em;'></div></div>to stand or be situated in (<span>loc.</span>; applied to heavenly bodies), &nbsp;<span class='ls'>VarBṛS.</span>&nbsp;; <div style='margin-top:0.6em;'></div></div>to associate or have intercourse with (<span>instr.</span>), &nbsp;<span class='ls'>BhP.</span>&nbsp;; <div style='margin-top:0.6em;'></div></div>to act, proceed, behave, live, &nbsp;<span class='ls'>MBh.</span>&nbsp;; &nbsp;<span class='ls'>Pañcat.</span>&nbsp;; <div style='margin-top:0.6em;'></div></div>to practise, perform, accomplish, make, do, &nbsp;<span class='ls'>Mn.</span>&nbsp;; &nbsp;<span class='ls'>MBh.</span>&nbsp; &c.; <div style='margin-top:0.6em;'></div></div>to graze upon, feed upon (a pasture), &nbsp;<span class='ls'>Bālar.</span>&nbsp; : <div style='margin-top:0.6em;'></div></div><strong><span>Caus.</span></strong> <span class='sdata'>-cārayati</span>, to cause to go or roam about, &nbsp;<span class='ls'>MBh.</span>&nbsp;; &nbsp;<span class='ls'>R.</span>&nbsp;; <div style='margin-top:0.6em;'></div></div>to cause to go astray, seduce, &nbsp;<span class='ls'>R.</span>&nbsp;; <div style='margin-top:0.6em;'></div></div>to move hither and thither (in the mind), ponder, reflect, consider, &nbsp;<span class='ls'>Mn.</span>&nbsp;; &nbsp;<span class='ls'>MBh.</span>&nbsp; &c.; <div style='margin-top:0.6em;'></div></div>to doubt, hesitate, &nbsp;<span class='ls'>ib.</span>&nbsp;; <div style='margin-top:0.6em;'></div></div>to examine, investigate, ascertain, &nbsp;<span class='ls'>ib.</span>&nbsp;","evidence":{"band":2,"band_label":"frequent -- learn early","rank_all":1496,"count_all":465,"first_era":"Vedic","genre":null,"example":{"sa":"vicaran","ru":"пребывал","work":"12_mahabharata-shantiparva","passage":"12.2.19-29","kind":"translation","source":"corpus_lexicon.jsonl (pwg_ru Phase 4, SanskritLexicography/RussianTranslation)"},"badges":[{"field":"band","value":2,"label":"frequent -- learn early","source":"kosha frequency layer, rank_all (DCS archive.sqlite M9 via VisualDCS)"},{"field":"count_all","value":465,"label":"465 attestations in DCS","source":"DCS archive.sqlite M9 (VisualDCS)"},{"field":"first_era","value":"Vedic","label":"first attested: Vedic","source":"DCS archive.sqlite M9 (VisualDCS)"},{"field":"genre","value":null,"label":"genre sketch not derivable from current DCS extraction (only a chronological period vector is stored, no per-genre breakdown)","source":"n/a -- gap documented, not fabricated (see app/evidence.py)"}]}},{"dict":"ap90","L":"25760","sense_ids":["ap90.25760.1@0.1.0-dev","ap90.25760.2@0.1.0-dev","ap90.25760.3@0.1.0-dev","ap90.25760.4@0.1.0-dev","ap90.25760.5@0.1.0-dev","ap90.25760.6@0.1.0-dev","ap90.25760.7@0.1.0-dev","ap90.25760.8@0.1.0-dev","ap90.25760.9@0.1.0-dev","ap90.25760.10@0.1.0-dev","ap90.25760.11@0.1.0-dev","ap90.25760.12@0.1.0-dev","ap90.25760.13@0.1.0-dev","ap90.25760.14@0.1.0-dev","ap90.25760.15@0.1.0-dev","ap90.25760.16@0.1.0-dev"],"scan_url":"https://sanskrit-lexicon.uni-koeln.de/scans/AP90Scan/2020/web/webtc/servepdf.php?page=969","headword":"vicar","rendered_html":"<span class='sdata'>vicar</span> 1 <span>P.</span> <div style='margin-top:0.6em;'></div></div><strong>1</strong> To wander about, roam over (<span>oft.</span> with <span>acc.</span>); <span class='sdata'>iṣṭāndeśān vicara jalada</span> &nbsp;<span class='ls'>Me. 115</span>&nbsp;; <span class='sdata'>vicacāra dāvaṃ</span> &nbsp;<span class='ls'>R. 2. 8</span>&nbsp;; &nbsp;<span class='ls'>Ku. 3. 31.</span>&nbsp; <div style='margin-top:0.6em;'></div></div><strong>2</strong> To do, perform, practise. <div style='margin-top:0.6em;'></div></div><strong>3</strong> To act, deal, behave. <div style='margin-top:0.6em;'></div></div><strong>4</strong> To deviate from the right path, go about wantonly; <br/>(<span title='Page 0969-c' style='border-bottom: 1px dotted #000; text-decoration: none;'>pb</span>) &nbsp;<span class='ls'>Ms. 9. 20.</span>&nbsp; <div style='margin-top:0.6em;'></div></div><strong>5</strong> To pass through, pervade. <div style='margin-top:0.6em;'></div></div><strong>6</strong> To attack, march against. <div style='margin-top:0.6em;'></div></div><strong>7</strong> To associate or have intercourse with. <div style='margin-top:0.6em;'></div></div><strong>8</strong> To go badly, fail. <div style='margin-top:0.6em;'></div></div><i>— <span>Caus.</span></i> <div style='margin-top:0.6em;'></div></div><strong>1</strong> To think, reflect or meditate upon. <div style='margin-top:0.6em;'></div></div><strong>2</strong> To discuss, call in question, debate; <span class='sdata'>ājñā gurūṇāṃ hyavicāraṇīyā</span> &nbsp;<span class='ls'>R. 14. 46.</span>&nbsp; <div style='margin-top:0.6em;'></div></div><strong>3</strong> To calculate, estimate; take into account, consider; <span class='sdata'>pareṣāmātmanaścaiva yo</span> <span class='sdata'>vicārya balābalaṃ</span> &nbsp;<span class='ls'>Pt. 3</span>&nbsp;; <span class='sdata'>suvicārya yatkṛtaṃ</span> &nbsp;<span class='ls'>H. 1. 22.</span>&nbsp; <div style='margin-top:0.6em;'></div></div><strong>4</strong> To hesitate, doubt. <div style='margin-top:0.6em;'></div></div><strong>5</strong> To examine, investigate. <div style='margin-top:0.6em;'></div></div><strong>6</strong> To seduce.","evidence":{"band":2,"band_label":"frequent -- learn early","rank_all":1496,"count_all":465,"first_era":"Vedic","genre":null,"example":{"sa":"vicaran","ru":"пребывал","work":"12_mahabharata-shantiparva","passage":"12.2.19-29","kind":"translation","source":"corpus_lexicon.jsonl (pwg_ru Phase 4, SanskritLexicography/RussianTranslation)"},"badges":[{"field":"band","value":2,"label":"frequent -- learn early","source":"kosha frequency layer, rank_all (DCS archive.sqlite M9 via VisualDCS)"},{"field":"count_all","value":465,"label":"465 attestations in DCS","source":"DCS archive.sqlite M9 (VisualDCS)"},{"field":"first_era","value":"Vedic","label":"first attested: Vedic","source":"DCS archive.sqlite M9 (VisualDCS)"},{"field":"genre","value":null,"label":"genre sketch not derivable from current DCS extraction (only a chronological period vector is stored, no per-genre breakdown)","source":"n/a -- gap documented, not fabricated (see app/evidence.py)"}]}}]}